{"id":652,"name":"Ручка для микроблейдинга","description":"Используется в волосковой и теневой технике перманентного макияжа, а также для стрелок и перманентного макияжа губ. Безболезненный и быстро заживающий способ татуажа. Надежная фиксация иглы в более экономичном варианте.","price":"15.0","display_price":"руб.15","available_on":"2017-04-06T00:00:00.000Z","slug":"ruchka-dlya-mikrobleydinga","meta_description":null,"meta_keywords":null,"shipping_category_id":1,"taxon_ids":[140],"total_on_hand":0,"br_price":"0.0","has_variants":false,"master":{"id":668,"name":"Ручка для микроблейдинга","sku":"AV-0037","price":"15.0","weight":"0.0","height":null,"width":null,"depth":null,"is_master":true,"slug":"ruchka-dlya-mikrobleydinga","description":"Используется в волосковой и теневой технике перманентного макияжа, а также для стрелок и перманентного макияжа губ. Безболезненный и быстро заживающий способ татуажа. Надежная фиксация иглы в более экономичном варианте.","track_inventory":true,"display_price":"руб.15","options_text":"","in_stock":false,"is_backorderable":true,"total_on_hand":0,"is_destroyed":false,"option_values":[],"images":[{"id":1039,"position":1,"attachment_content_type":"image/jpeg","attachment_file_name":"microruchki07-500x500-product_popup.jpg","type":"Spree::Image","attachment_updated_at":"2017-04-06T15:16:04.382Z","attachment_width":500,"attachment_height":500,"alt":"","viewable_type":"Spree::Variant","viewable_id":668,"mini_url":"/spree/products/1039/mini/microruchki07-500x500-product_popup.jpg?1491491764","small_url":"/spree/products/1039/small/microruchki07-500x500-product_popup.jpg?1491491764","product_url":"/spree/products/1039/product/microruchki07-500x500-product_popup.jpg?1491491764","large_url":"/spree/products/1039/large/microruchki07-500x500-product_popup.jpg?1491491764"}]},"variants":[],"option_types":[],"product_properties":[{"id":2461,"product_id":652,"property_id":31,"value":null,"property_name":"Вес"},{"id":2462,"product_id":652,"property_id":32,"value":null,"property_name":"Цвет"},{"id":2463,"product_id":652,"property_id":33,"value":null,"property_name":"рабочий ход"}],"classifications":[{"taxon_id":140,"position":2,"taxon":{"id":140,"name":"Ручки ","pretty_name":"Микроблейдинг  -> Ручки ","permalink":"mikroblieidingh/ruchki","parent_id":125,"taxonomy_id":22,"taxons":[]}}]}