{"name":"Комплект от InkMachines","id":200,"slug":"komplekt-ot-inkmachines","description":"<span class=\"red\"><i>ПОД ЗАКАЗ</i></span>\r\n\r\nКомплект от <span class=\"bold\">InkMachines - \"RPS-600 Wireless Power Supply\"</span>\r\n\r\nПодходят любые педали и шнуры \r\n\r\nLCD Дисплей 2,7' (60х33мм) \r\n\r\nВес одного аккумулятора - 65 г \r\n\r\nЗарядки каждого аккумулятора хватает примерно на 5 часов \r\n\r\nУ каждого аккумулятора примерно 500 циклов заряда \r\n\r\nАккумуляторы подходят для машинок Dragonfly и Stingray \r\n\r\nВремя заряда аккумулятора - около 1 часа \r\n\r\nБеспроводная педаль в комплекте \r\n\r\nUSB - только для обновленного программного обеспечения \r\n\r\nРабочая температура - 10-35 ̊C для использования в помещениях \r\n\r\nМощность - 100-240V 50-60Hz \r\n\r\nМощность при дистанционном подключении: 5-13B \r\n\r\nМощность при прямом подключении: 4-18В","article":"SO-006","externalImages":["0.jpeg","1.jpeg","2.jpeg","3.jpeg","4.jpeg","5.jpeg","6.jpeg","7.jpeg","8.jpeg","9.jpeg","10.jpeg"],"price":0,"properties":[{"key":"Производство","value":"InkMachines (Швеция)"}]}