{"id":905,"name":"Vantablack 306 (Самый черный)","description":"Холодный оттенок.\r\nСамый черный, насыщенный и плотный цвет.\r\nПозволяет делать очень яркие стрелки.\r\nНе рекомендуется использовать в чистом виде.","price":"35.0","display_price":"руб.35","available_on":"2017-09-28T00:00:00.000Z","slug":"vantablack-306-samyy-chernyy","meta_description":null,"meta_keywords":null,"shipping_category_id":1,"taxon_ids":[148],"total_on_hand":0,"br_price":"0.0","has_variants":false,"master":{"id":921,"name":"Vantablack 306 (Самый черный)","sku":"QO-006","price":"35.0","weight":"0.0","height":null,"width":null,"depth":null,"is_master":true,"slug":"vantablack-306-samyy-chernyy","description":"Холодный оттенок.\r\nСамый черный, насыщенный и плотный цвет.\r\nПозволяет делать очень яркие стрелки.\r\nНе рекомендуется использовать в чистом виде.","track_inventory":true,"display_price":"руб.35","options_text":"","in_stock":false,"is_backorderable":true,"total_on_hand":0,"is_destroyed":false,"option_values":[],"images":[{"id":1346,"position":1,"attachment_content_type":"image/jpeg","attachment_file_name":"306.jpg","type":"Spree::Image","attachment_updated_at":"2017-09-28T14:28:00.491Z","attachment_width":900,"attachment_height":800,"alt":"","viewable_type":"Spree::Variant","viewable_id":921,"mini_url":"/spree/products/1346/mini/306.jpg?1506608880","small_url":"/spree/products/1346/small/306.jpg?1506608880","product_url":"/spree/products/1346/product/306.jpg?1506608880","large_url":"/spree/products/1346/large/306.jpg?1506608880"}]},"variants":[],"option_types":[],"product_properties":[],"classifications":[{"taxon_id":148,"position":6,"taxon":{"id":148,"name":"Пигменты Qolora","pretty_name":"Перманентный макияж -> Пигменты Qolora","permalink":"piermanientnyi-makiiazh/pighmienty-qolora","parent_id":40,"taxonomy_id":17,"taxons":[]}}]}