{"name":"Sorry Mom HOLD FAST (Трансферный гель) 100 ml","id":341,"slug":"sorry-mom-hold-fast-transfernyy-gel-100-ml","description":"Легкий гель для переноса трансфера. Разработанн при участии  Myke Chambers - одного из основоположников традиционного стиля татуировки.\r\n\r\nПрост в применении\r\nДолго держит трансфер на коже\r\nСодержит экстракт Алое Вера, успокаивающий кожу\r\nРаботает с любой трансферной бумагой и маркерами\r\nЭкономично расходуется, капли размером с десятикопеечную монету хватает на среднее предплечье\r\nБезопасен для любых типов кожи, не токсичен\r\nУпаковка в 100мл идеальна для путешествий.\r\n\r\nИнструкция по применению: Обезжирить кожу, нанести немного геля и растереть. Аккуратно приложить трансфер и подождать 15-20 минут.\r\n\r\nПроизведено в Дании.","article":"SY-0054","externalImages":["0.jpeg"],"price":17.5,"properties":[]}