{"id":"tf01","name":"Turanium Fabrica - Space Velvet","description":"Новинка нашего каталога Turanium! <span class=\"bold\">TURANIUM Tattoo Machine</span> - высоко качественная роторная машина, сделанная в Венгрии. Она обеспечивает безопасную и бесперебойную работу. Она идеально подходит для каждого вида работы, покрас, тени, линии. <span class=\"bold\">Технические характеристики</span> 1. Turanium машина оснащена разъемом RCA, который обеспечивает отличную проводимость, постоянное напряжение и невозможность поменять полярность на разъеме. 2. Машина оснащена известным швейцарским движком Maxon 5Вт. 3. Ход-3,6 мм в стандартной комплектации. Корпус машины из авиационного алюминия. 4. Рекомендуемое рабочее напряжение 6,5-10 Вт. Как с любой роторной машины, мы рекомендуем использовать профессиональные источники питания для татуировки. Эти источники питания обеспечивают постоянное, стабильное питание и чистый сигнал, который увеличивает и усиливает двигателя. Машина была разработана для классических игл и трубок, татуировки, но также хорошо работает с картриджами.","article":"TF01","externalImages":["0.jpeg"],"price":360,"properties":[{"key":"Код цвета","value":"TF01"},{"key":"Рекомендуемое операционное напряжение","value":"6,5-10W"},{"key":"Ход машины","value":"3,6 мм"},{"key":"Гарантия","value":"6 месяцев"},{"key":"Производитель","value":"TURANIUM Fabrika Rotary (Венгрия)"}]}