{"id":777,"name":"Rejuvi Hyaluronic Acid Serum","description":"Гиалуроновая сыворотка В большинстве случаев препараты с гиалуроновой кислотой с большой молекулой, поэтому проникновение препарата не так эффективно, как могло бы быть. Rejuvi Hyaluronic Acid Serum - эффективная сыворотка с низкомолекулярной высококонцентрированной гиалуроновой кислотой, что способствует легкому проникновению в кожу и очень эффективно увлажняет клетки. Сыворотка - биполярна, тем самым подходит не только под дермароллер (рекомендовано), дермапен и любой микронидлинг, но и под любые аппаратные методики (гальваника, ультразвук и т.д). После нанесения не липнет, и на коже остается только приятное ощущение увлажнённости.","price":"50.0","display_price":"руб.50","available_on":"2017-06-24T00:00:00.000Z","slug":"rejuvi-hyaluronic-acid-serum","meta_description":null,"meta_keywords":"rejuvi","shipping_category_id":1,"taxon_ids":[123],"total_on_hand":0,"br_price":"0.0","has_variants":false,"master":{"id":793,"name":"Rejuvi Hyaluronic Acid Serum","sku":"R-002","price":"50.0","weight":"0.0","height":null,"width":null,"depth":null,"is_master":true,"slug":"rejuvi-hyaluronic-acid-serum","description":"Гиалуроновая сыворотка В большинстве случаев препараты с гиалуроновой кислотой с большой молекулой, поэтому проникновение препарата не так эффективно, как могло бы быть. Rejuvi Hyaluronic Acid Serum - эффективная сыворотка с низкомолекулярной высококонцентрированной гиалуроновой кислотой, что способствует легкому проникновению в кожу и очень эффективно увлажняет клетки. Сыворотка - биполярна, тем самым подходит не только под дермароллер (рекомендовано), дермапен и любой микронидлинг, но и под любые аппаратные методики (гальваника, ультразвук и т.д). После нанесения не липнет, и на коже остается только приятное ощущение увлажнённости.","track_inventory":true,"display_price":"руб.50","options_text":"","in_stock":false,"is_backorderable":true,"total_on_hand":0,"is_destroyed":false,"option_values":[],"images":[{"id":1189,"position":1,"attachment_content_type":"image/jpeg","attachment_file_name":"Hyaluronic-Acid-Serum.jpg","type":"Spree::Image","attachment_updated_at":"2017-06-24T09:30:30.549Z","attachment_width":600,"attachment_height":600,"alt":"","viewable_type":"Spree::Variant","viewable_id":793,"mini_url":"/spree/products/1189/mini/Hyaluronic-Acid-Serum.jpg?1498296630","small_url":"/spree/products/1189/small/Hyaluronic-Acid-Serum.jpg?1498296630","product_url":"/spree/products/1189/product/Hyaluronic-Acid-Serum.jpg?1498296630","large_url":"/spree/products/1189/large/Hyaluronic-Acid-Serum.jpg?1498296630"}]},"variants":[],"option_types":[],"product_properties":[{"id":2595,"product_id":777,"property_id":3853,"value":"30 ml","property_name":"Обьем"},{"id":2596,"product_id":777,"property_id":3854,"value":null,"property_name":"Количество"},{"id":2597,"product_id":777,"property_id":3855,"value":"США","property_name":"Производитель"},{"id":2598,"product_id":777,"property_id":3856,"value":null,"property_name":"ОБьем"}],"classifications":[{"taxon_id":123,"position":6,"taxon":{"id":123,"name":"Rejuvi","pretty_name":"Rejuvi","permalink":"rejuvi","parent_id":null,"taxonomy_id":21,"taxons":[]}}]}
