{"id":691,"name":"Пигмент NPM Caramel 18004","description":"Пигмент коллекции AREOLA COLOR COLLECTION Коллекция пигментов NPM, предназначенная для работы в области ареолярного комплекса. Коллекция цветов пигментов позволяет : маскировать дефекты в виде послеоперационных рубцов, шрамов на коже выполнять эстетические коррекции цвета и формы ареолы.","price":"65.0","display_price":"руб.65","available_on":"2017-04-14T00:00:00.000Z","slug":"pigment-npm-caramel-18004","meta_description":null,"meta_keywords":"Пигменты npm","shipping_category_id":1,"taxon_ids":[131],"total_on_hand":0,"br_price":"0.0","has_variants":false,"master":{"id":707,"name":"Пигмент NPM Caramel 18004","sku":"S-40","price":"65.0","weight":"0.0","height":null,"width":null,"depth":null,"is_master":true,"slug":"pigment-npm-caramel-18004","description":"Пигмент коллекции AREOLA COLOR COLLECTION Коллекция пигментов NPM, предназначенная для работы в области ареолярного комплекса. Коллекция цветов пигментов позволяет : маскировать дефекты в виде послеоперационных рубцов, шрамов на коже выполнять эстетические коррекции цвета и формы ареолы.","track_inventory":true,"display_price":"руб.65","options_text":"","in_stock":false,"is_backorderable":true,"total_on_hand":0,"is_destroyed":false,"option_values":[],"images":[{"id":1088,"position":1,"attachment_content_type":"image/jpeg","attachment_file_name":"Без_имени-1.jpg","type":"Spree::Image","attachment_updated_at":"2017-04-15T12:55:52.065Z","attachment_width":704,"attachment_height":704,"alt":"","viewable_type":"Spree::Variant","viewable_id":707,"mini_url":"/spree/products/1088/mini/%D0%91%D0%B5%D0%B7_%D0%B8%D0%BC%D0%B5%D0%BD%D0%B8-1.jpg?1492260952","small_url":"/spree/products/1088/small/%D0%91%D0%B5%D0%B7_%D0%B8%D0%BC%D0%B5%D0%BD%D0%B8-1.jpg?1492260952","product_url":"/spree/products/1088/product/%D0%91%D0%B5%D0%B7_%D0%B8%D0%BC%D0%B5%D0%BD%D0%B8-1.jpg?1492260952","large_url":"/spree/products/1088/large/%D0%91%D0%B5%D0%B7_%D0%B8%D0%BC%D0%B5%D0%BD%D0%B8-1.jpg?1492260952"}]},"variants":[],"option_types":[],"product_properties":[],"classifications":[{"taxon_id":131,"position":7,"taxon":{"id":131,"name":"Пигменты NPM","pretty_name":"Перманентный макияж -> Пигменты NPM","permalink":"piermanientnyi-makiiazh/pighmienty-npm","parent_id":40,"taxonomy_id":17,"taxons":[]}}]}