{"id":914,"name":"Aloe Green Soap с Аллантоином ( Концентрат зеленого мыла 1000 мл)","description":"Концентрат зеленого мыла с pH 5,5. Эффективно удаляет излишки краски. Содержит экстракт листьев алоэ и аллантоин.\r\n\r\nАллантоин - природный анестетик, ускоряющий заживление ран.\r\nЭкстракт алое увлажняет и успокаивает кожу.\r\n\r\nКонцентрат расходуется экономно, разводить его нужно 1 к 10. \r\nПрименение этого мыла во время сеанса татуировки оказывает увлажняющее, успокаивающее и противоотечное действие. ","price":"25.0","display_price":"руб.25","available_on":"2017-10-06T00:00:00.000Z","slug":"aloe-green-soap-s-allantoinom-kontsentrat-zelenogo-myla-1000-ml","meta_description":null,"meta_keywords":null,"shipping_category_id":1,"taxon_ids":[142],"total_on_hand":0,"br_price":"0.0","has_variants":false,"master":{"id":930,"name":"Aloe Green Soap с Аллантоином ( Концентрат зеленого мыла 1000 мл)","sku":"SY-0052","price":"25.0","weight":"0.0","height":null,"width":null,"depth":null,"is_master":true,"slug":"aloe-green-soap-s-allantoinom-kontsentrat-zelenogo-myla-1000-ml","description":"Концентрат зеленого мыла с pH 5,5. Эффективно удаляет излишки краски. Содержит экстракт листьев алоэ и аллантоин.\r\n\r\nАллантоин - природный анестетик, ускоряющий заживление ран.\r\nЭкстракт алое увлажняет и успокаивает кожу.\r\n\r\nКонцентрат расходуется экономно, разводить его нужно 1 к 10. \r\nПрименение этого мыла во время сеанса татуировки оказывает увлажняющее, успокаивающее и противоотечное действие. ","track_inventory":true,"display_price":"руб.25","options_text":"","in_stock":false,"is_backorderable":true,"total_on_hand":0,"is_destroyed":false,"option_values":[],"images":[{"id":1355,"position":1,"attachment_content_type":"image/jpeg","attachment_file_name":"Без_имени-1.jpg","type":"Spree::Image","attachment_updated_at":"2017-10-06T14:02:23.939Z","attachment_width":900,"attachment_height":800,"alt":"","viewable_type":"Spree::Variant","viewable_id":930,"mini_url":"/spree/products/1355/mini/%D0%91%D0%B5%D0%B7_%D0%B8%D0%BC%D0%B5%D0%BD%D0%B8-1.jpg?1507298543","small_url":"/spree/products/1355/small/%D0%91%D0%B5%D0%B7_%D0%B8%D0%BC%D0%B5%D0%BD%D0%B8-1.jpg?1507298543","product_url":"/spree/products/1355/product/%D0%91%D0%B5%D0%B7_%D0%B8%D0%BC%D0%B5%D0%BD%D0%B8-1.jpg?1507298543","large_url":"/spree/products/1355/large/%D0%91%D0%B5%D0%B7_%D0%B8%D0%BC%D0%B5%D0%BD%D0%B8-1.jpg?1507298543"}]},"variants":[],"option_types":[],"product_properties":[],"classifications":[{"taxon_id":142,"position":17,"taxon":{"id":142,"name":"Мыло и пена ","pretty_name":"Мыло и пена ","permalink":"mylo-i-piena","parent_id":null,"taxonomy_id":26,"taxons":[]}}]}