{"id":"s-70","name":"Nocturnal Super Black","description":"Nocturnal Tattoo Ink \"Super Black\"Крайне полезный пигмент, когда художник пытается достигнуть самого темного черного цвета. Черные как уголь Super Black подойдет даже для племенных татуировок в полинезийском стиле, майори и т.д., действенен для всего, что должно быть максимально черно. Его очень полезно использовать с грей вошами из линейки West Coast blend ink: темные, средние и легкие тона, чтобы работать с полным спектром черно-серой палитры. Производство: США Объём: 240 мл","article":"S-70","externalImages":["0.jpeg"],"price":50,"properties":[{"key":"Обьем","value":null},{"key":"Количество","value":null},{"key":"Материал","value":null},{"key":"Производитель","value":null}]}