{"name":"GREEN CONC - ETERNAL","id":"3694","slug":"green-conc-eternal-3694","description":"Концентрированный зеленый тату-пигмент. Применяется в пейзажных темах. Возможно применение, как есть, а также осветление и смешивание с синими, желтыми и другими оттенками палитры. После заживления смотрится очень темно-зеленым. Применяется в кавер-ап работах.","article":"3694","externalImages":["0.jpeg"],"price":40,"properties":[{"key":"Код цвета","value":"3694"},{"key":"Цвет пигмента","value":"Green Conc (Насыщенный зеленый)"},{"key":"Производитель","value":"Eternal Ink (США)"}]}