{"id":651,"name":"Ручка для микроблейдинга двусторонняя ","description":"Двустороння ручка манипула для микроблейдинга.\r\n\r\nИмеет два металлических цанговых зажима, что\r\n\r\nнесомненно удобно при стерилизации этого\r\n\r\nэлемента ручки.","price":"20.0","display_price":"руб.20","available_on":"2017-04-06T00:00:00.000Z","slug":"ruchka-dlya-mikrobleydinga-dvustoronnyaya","meta_description":null,"meta_keywords":null,"shipping_category_id":1,"taxon_ids":[140],"total_on_hand":0,"br_price":"0.0","has_variants":false,"master":{"id":667,"name":"Ручка для микроблейдинга двусторонняя ","sku":"AV-0036","price":"20.0","weight":"0.0","height":null,"width":null,"depth":null,"is_master":true,"slug":"ruchka-dlya-mikrobleydinga-dvustoronnyaya","description":"Двустороння ручка манипула для микроблейдинга.\r\n\r\nИмеет два металлических цанговых зажима, что\r\n\r\nнесомненно удобно при стерилизации этого\r\n\r\nэлемента ручки.","track_inventory":true,"display_price":"руб.20","options_text":"","in_stock":false,"is_backorderable":true,"total_on_hand":0,"is_destroyed":false,"option_values":[],"images":[{"id":1038,"position":1,"attachment_content_type":"image/jpeg","attachment_file_name":"ruchky-dlya-mykrobleydynga-6d-brov-v-assortymente-kyev-dostavka__41450359m.jpg","type":"Spree::Image","attachment_updated_at":"2017-04-06T15:07:33.773Z","attachment_width":640,"attachment_height":480,"alt":"","viewable_type":"Spree::Variant","viewable_id":667,"mini_url":"/spree/products/1038/mini/ruchky-dlya-mykrobleydynga-6d-brov-v-assortymente-kyev-dostavka__41450359m.jpg?1491491253","small_url":"/spree/products/1038/small/ruchky-dlya-mykrobleydynga-6d-brov-v-assortymente-kyev-dostavka__41450359m.jpg?1491491253","product_url":"/spree/products/1038/product/ruchky-dlya-mykrobleydynga-6d-brov-v-assortymente-kyev-dostavka__41450359m.jpg?1491491253","large_url":"/spree/products/1038/large/ruchky-dlya-mykrobleydynga-6d-brov-v-assortymente-kyev-dostavka__41450359m.jpg?1491491253"}]},"variants":[],"option_types":[],"product_properties":[{"id":2458,"product_id":651,"property_id":31,"value":null,"property_name":"Вес"},{"id":2459,"product_id":651,"property_id":32,"value":null,"property_name":"Цвет"},{"id":2460,"product_id":651,"property_id":33,"value":null,"property_name":"рабочий ход"}],"classifications":[{"taxon_id":140,"position":1,"taxon":{"id":140,"name":"Ручки ","pretty_name":"Микроблейдинг  -> Ручки ","permalink":"mikroblieidingh/ruchki","parent_id":125,"taxonomy_id":22,"taxons":[]}}]}